sportradar/__init__.py
sportradar/nfl/__init__.py
sportradar/nfl/extract/__init__.py
sportradar/nfl/extract/additionalfeeds.py
sportradar/nfl/extract/draftfeeds.py
sportradar/nfl/extract/gamefeeds.py
sportradar/nfl/extract/playerfeeds.py
sportradar/nfl/extract/primaryfeeds.py
sportradar/nfl/extract/teamfeeds.py
sportradar/nfl/simulation/__init__.py
sportradar/nfl/simulation/available_recordings.py
sportradar/nfl/simulation/config.py
sportradar/nfl/simulation/gamefeeds.py
sportradar/nfl/simulation/session.py
sportradar/nfl/transform/__init__.py
sportradar/nfl/transform/additionalfeeds.py
sportradar/nfl/transform/draftfeeds.py
sportradar/nfl/transform/gamefeeds.py
sportradar/nfl/transform/playerfeeds.py
sportradar/nfl/transform/primaryfeeds.py
sportradar/nfl/transform/teamfeeds.py
sportradar/nfl/workspace/__init__.py
sportradar/nfl/workspace/datastore.py
sportradar/nfl/workspace/resource_cache.py
sportradar_tests/__init__.py
sportradar_tests/nfl/__init__.py
sportradar_tests/nfl/extract/__init__.py
sportradar_tests/nfl/extract/additionalfeeds_test.py
sportradar_tests/nfl/extract/draftfeeds_test.py
sportradar_tests/nfl/extract/gamefeeds_test.py
sportradar_tests/nfl/extract/playerfeeds_test.py
sportradar_tests/nfl/extract/primaryfeeds_test.py
sportradar_tests/nfl/extract/teamfeeds_test.py
sportradar_tests/nfl/simulation/__init__.py
sportradar_tests/nfl/simulation/available_recordings_test.py
sportradar_tests/nfl/simulation/gamefeeds_test.py
sportradar_tests/nfl/simulation/session_test.py
sportradar_tests/nfl/transform/__init__.py
sportradar_tests/nfl/transform/additionalfeeds_test.py
sportradar_tests/nfl/transform/draftfeeds_test.py
sportradar_tests/nfl/transform/gamefeeds_test.py
sportradar_tests/nfl/transform/playerfeeds_test.py
sportradar_tests/nfl/transform/primaryfeeds_test.py
sportradar_tests/nfl/transform/teamfeeds_test.py
sportradar_tests/nfl/workspace/__init__.py
sportradar_tests/nfl/workspace/resource_cache_test.py
sportradar_unofficial-0.1.15.dist-info/LICENSE.txt
sportradar_unofficial-0.1.15.dist-info/METADATA
sportradar_unofficial-0.1.15.dist-info/WHEEL
sportradar_unofficial-0.1.15.dist-info/top_level.txt
sportradar_unofficial-0.1.15.dist-info/RECORD
