Metadata-Version: 2.1
Name: sportradar-unofficial
Version: 0.1.15
Summary: An unofficial python package to access sportradar NFL APIs.
Home-page: http://github.com/ggurjar333/sportradar-unofficial
Author: Gaurav Gurjar, John Bonnett, John Bassie
Author-email: ggurjar333@gmail.com
License: MIT
Keywords: sport analysis,sport statistics,sport data analysis,scraping,data collection,data processing,MongoDB
License-File: LICENSE.txt
Requires-Dist: urllib3
Requires-Dist: pydantic
Requires-Dist: requests
Requires-Dist: pymongo
Requires-Dist: redis
Requires-Dist: python-dotenv
